memberjojo/__init__.py
memberjojo/_version.py
memberjojo/mojo_common.py
memberjojo/mojo_loader.py
memberjojo/mojo_member.py
memberjojo/mojo_transaction.py
memberjojo-2.2.dist-info/licenses/LICENSE
memberjojo-2.2.dist-info/WHEEL
memberjojo-2.2.dist-info/METADATA
memberjojo-2.2.dist-info/RECORD
