Metadata-Version: 2.4
Name: memberjojo
Version: 2.2
Summary: memberjojo - tools for working with members.
Author-email: Duncan Bellamy <dunk@denkimushi.com>
Requires-Python: >=3.8
License-Expression: MIT
License-File: LICENSE
Requires-Dist: sqlcipher3
Requires-Dist: coverage ; extra == "dev"
Requires-Dist: flit ; extra == "dev"
Requires-Dist: pytest ; extra == "dev"
Requires-Dist: furo ; extra == "docs"
Requires-Dist: myst-parser>=2.0 ; extra == "docs"
Requires-Dist: sphinx>=7.0 ; extra == "docs"
Requires-Dist: sphinx-autodoc-typehints ; extra == "docs"
Requires-Dist: black ; extra == "lint"
Requires-Dist: pylint ; extra == "lint"
Project-URL: Home, https://github.com/a16bitsysop/memberjojo
Provides-Extra: dev
Provides-Extra: docs
Provides-Extra: lint
